<?xml version="1.0" encoding="utf-8"?>
<StatusEffectHolder xmlns:xsd="http://www.w3.org/2001/XMLSchema" xmlns:xsi="http://www.w3.org/2001/XMLSchema-instance">
  <Name>Luxurious Tent buff</Name>
  <PresetID>525</PresetID>
  <Lifespan>2400</Lifespan>
  <LengthType>Short</LengthType>
  <Tags />
  <CanBeHealedBySleeping>false</CanBeHealedBySleeping>
  <StraightSleepHealTime>-1</StraightSleepHealTime>
  <Effects>
    <EffectHolder xsi:type="AffectStatHolder">
      <AffectedStat>StaminaCostReduction</AffectedStat>
      <AffectedStat_TagUID>150</AffectedStat_TagUID>
      <AffectQuantity>20</AffectQuantity>
      <IsModifier>true</IsModifier>
    </EffectHolder>
  </Effects>
</StatusEffectHolder>