<?xml version="1.0" encoding="utf-8"?>
<StatusEffectHolder xmlns:xsd="http://www.w3.org/2001/XMLSchema" xmlns:xsi="http://www.w3.org/2001/XMLSchema-instance">
  <Name>Warm Amplified</Name>
  <PresetID>70</PresetID>
  <Lifespan>240</Lifespan>
  <LengthType>Short</LengthType>
  <Tags>
    <string>Warm</string>
    <string>Boon</string>
    <string>Status Type</string>
  </Tags>
  <CanBeHealedBySleeping>false</CanBeHealedBySleeping>
  <StraightSleepHealTime>-1</StraightSleepHealTime>
  <Effects>
    <EffectHolder xsi:type="AffectStatHolder">
      <AffectedStat>FireDamage</AffectedStat>
      <AffectedStat_TagUID>102</AffectedStat_TagUID>
      <AffectQuantity>30</AffectQuantity>
      <IsModifier>true</IsModifier>
    </EffectHolder>
    <EffectHolder xsi:type="AffectStatHolder">
      <AffectedStat>EnvColdProtection</AffectedStat>
      <AffectedStat_TagUID>123</AffectedStat_TagUID>
      <AffectQuantity>16</AffectQuantity>
      <IsModifier>false</IsModifier>
    </EffectHolder>
    <EffectHolder xsi:type="AffectStatHolder">
      <AffectedStat>FireResistance</AffectedStat>
      <AffectedStat_TagUID>118</AffectedStat_TagUID>
      <AffectQuantity>30</AffectQuantity>
      <IsModifier>false</IsModifier>
    </EffectHolder>
  </Effects>
</StatusEffectHolder>