<?xml version="1.0" encoding="utf-8"?>
<DM_Recipe xmlns:xsd="http://www.w3.org/2001/XMLSchema" xmlns:xsi="http://www.w3.org/2001/XMLSchema-instance">
  <Name>Horror Greataxe</Name>
  <RecipeID>326</RecipeID>
  <UID />
  <StationType>Survival</StationType>
  <RequiredPType>None</RequiredPType>
  <Ingredients>
    <string>Fang Greataxe</string>
    <string>Horror Chitin</string>
    <string>Occult Remains</string>
    <string>Palladium Scrap</string>
  </Ingredients>
  <Results>
    <ItemQty>
      <ItemName>Horror Greataxe</ItemName>
      <ItemID>2110120</ItemID>
      <Quantity>1</Quantity>
    </ItemQty>
  </Results>
</DM_Recipe>