<?xml version="1.0" encoding="utf-8"?>
<DM_Recipe xmlns:xsd="http://www.w3.org/2001/XMLSchema" xmlns:xsi="http://www.w3.org/2001/XMLSchema-instance">
  <Name>Palladium Scrap</Name>
  <RecipeID>41</RecipeID>
  <UID />
  <StationType>Survival</StationType>
  <RequiredPType>None</RequiredPType>
  <Ingredients>
    <string>DecraftPalladium_Small</string>
  </Ingredients>
  <Results>
    <ItemQty>
      <ItemName>Palladium Scrap</ItemName>
      <ItemID>6400070</ItemID>
      <Quantity>1</Quantity>
    </ItemQty>
  </Results>
</DM_Recipe>