<?xml version="1.0" encoding="utf-8"?>
<RecipeHolder xmlns:xsi="http://www.w3.org/2001/XMLSchema-instance" xmlns:xsd="http://www.w3.org/2001/XMLSchema">
  <StationType>Survival</StationType>
  <Name>Poison Rag</Name>
  <RecipeID>99</RecipeID>
  <Ingredients>
    <string>Linen Cloth</string>
    <string>Grilled Crabeye Seed</string>
  </Ingredients>
  <Results>
    <ItemQuantityHolder>
      <ItemName>Poison Rag</ItemName>
      <Quantity>1</Quantity>
    </ItemQuantityHolder>
  </Results>
</RecipeHolder>