<?xml version="1.0" encoding="utf-8"?>
<SceneSummary xmlns:xsd="http://www.w3.org/2001/XMLSchema" xmlns:xsi="http://www.w3.org/2001/XMLSchema-instance">
  <SceneName>Royal Manticore’s Lair</SceneName>
  <Enemies>
    <QuantityHolder>
      <Name>Troglodyte Grenadier (1)</Name>
      <Quantity>1</Quantity>
    </QuantityHolder>
    <QuantityHolder>
      <Name>Troglodyte Knight (1)</Name>
      <Quantity>2</Quantity>
    </QuantityHolder>
    <QuantityHolder>
      <Name>Armored Troglodyte (1)</Name>
      <Quantity>2</Quantity>
    </QuantityHolder>
    <QuantityHolder>
      <Name>Troglodyte (1)</Name>
      <Quantity>3</Quantity>
    </QuantityHolder>
    <QuantityHolder>
      <Name>Manticore (1)</Name>
      <Quantity>2</Quantity>
    </QuantityHolder>
  </Enemies>
  <Merchants />
  <Loot_Containers>
    <QuantityHolder>
      <Name>Worker’s Corpse</Name>
      <Quantity>1</Quantity>
    </QuantityHolder>
    <QuantityHolder>
      <Name>Looter’s Corpse</Name>
      <Quantity>1</Quantity>
    </QuantityHolder>
    <QuantityHolder>
      <Name>Scavenger’s Corpse</Name>
      <Quantity>1</Quantity>
    </QuantityHolder>
    <QuantityHolder>
      <Name>Ornate Chest</Name>
      <Quantity>1</Quantity>
    </QuantityHolder>
    <QuantityHolder>
      <Name>Trog Chest</Name>
      <Quantity>1</Quantity>
    </QuantityHolder>
  </Loot_Containers>
  <Gatherables>
    <QuantityHolder>
      <Name>Tree</Name>
      <Quantity>3</Quantity>
    </QuantityHolder>
    <QuantityHolder>
      <Name>Star Mushroom</Name>
      <Quantity>3</Quantity>
    </QuantityHolder>
    <QuantityHolder>
      <Name>Smoke Root</Name>
      <Quantity>4</Quantity>
    </QuantityHolder>
    <QuantityHolder>
      <Name>Palladium vein</Name>
      <Quantity>2</Quantity>
    </QuantityHolder>
    <QuantityHolder>
      <Name>Iron vein</Name>
      <Quantity>2</Quantity>
    </QuantityHolder>
    <QuantityHolder>
      <Name>Blood Mushroom</Name>
      <Quantity>1</Quantity>
    </QuantityHolder>
  </Gatherables>
  <Item_Spawns>
    <DM_ItemSpawn>
      <Name>Zhorn’s Hunting Backpack</Name>
      <Item_ID>5300180</Item_ID>
      <Quantity>1</Quantity>
      <positions>
        <Vector3>
          <x>18.7977428</x>
          <y>20.02034</y>
          <z>-124.08844</z>
        </Vector3>
      </positions>
    </DM_ItemSpawn>
  </Item_Spawns>
  <UniqueContainerList>
    <string>Worker’s Corpse_VvehsClz8E2W_4YH1yY7Gw</string>
    <string>Looter’s Corpse_g3xgzMD23UKSUfDtThH_IA</string>
    <string>Scavenger’s Corpse_J1E_A3P4rESbnBUfSq-9aw</string>
    <string>Ornate Chest_gf64pkC4d0CBO0iEjivFFA</string>
    <string>Trog Chest_3VgK6PTWfkuX_0-MSePFQA</string>
  </UniqueContainerList>
</SceneSummary>