<?xml version="1.0" encoding="utf-8"?>
<ItemHolder xmlns:xsd="http://www.w3.org/2001/XMLSchema" xmlns:xsi="http://www.w3.org/2001/XMLSchema-instance" xsi:type="QuestHolder">
  <ItemID>7021009</ItemID>
  <Name>Item</Name>
  <gameObjectName>7021009_GlimpseOfThePast</gameObjectName>
  <saveDir>/Quest</saveDir>
  <Description />
  <LegacyItemID>-1</LegacyItemID>
  <Tags />
  <EffectTransforms />
  <SerializedCanvas>{"version":2.6,"type":"NodeCanvas.StateMachines.QuestTree","name":"GlimpseOfThePast","translation":{"x":-3390.0,"y":-3394.0},"zoomFactor":0.6842106,"nodes":[{"_actionList":{"executionMode":"ActionsRunInParallel","actions":[{"statement":{"_text":"With a greasy Fern, I can commune with my own ancestors at our family altar."},"logParameters":[],"$type":"NodeCanvas.Tasks.Actions.QuestAction_AddLogEntry"}]},"_position":{"x":5420.0,"y":5375.0},"$type":"NodeCanvas.StateMachines.QuestStep","$id":"2"},{"_actionList":{"executionMode":"ActionsRunInParallel","actions":[{"isSuccessful":{"_value":true},"$type":"NodeCanvas.Tasks.Actions.CompleteQuest"}]},"_position":{"x":6120.923,"y":5439.842},"$type":"NodeCanvas.StateMachines.QuestStep","$id":"7"}],"connections":[{"_condition":{"QuestEventRef":{"m_eventUID":"oF2ZWwnV5UC49isATwB-ow"},"$type":"NodeCanvas.Tasks.Conditions.Condition_QuestEventOccured"},"_sourceNode":{"$ref":"2"},"_targetNode":{"$ref":"7"},"$type":"NodeCanvas.StateMachines.FSMConnection"}],"primeNode":{"$ref":"2"},"localBlackboard":{"_name":"Local Blackboard","_variables":{}}}</SerializedCanvas>
</ItemHolder>