<?xml version="1.0" encoding="utf-8"?>
<DM_Item xmlns:xsd="http://www.w3.org/2001/XMLSchema" xmlns:xsi="http://www.w3.org/2001/XMLSchema-instance">
  <gameObjectName>4200050_BitterSpicyTea</gameObjectName>
  <saveDir>/Food</saveDir>
  <ItemID>4200050</ItemID>
  <Name>Bitter Spicy Tea</Name>
  <Description>Concoction that instantly cures infections, protects against the cold and restores burnt Stamina.</Description>
  <LegacyItemID>-1</LegacyItemID>
  <IsPickable>true</IsPickable>
  <IsUsable>true</IsUsable>
  <QtyRemovedOnUse>1</QtyRemovedOnUse>
  <GroupItemInDisplay>false</GroupItemInDisplay>
  <HasPhysicsWhenWorld>false</HasPhysicsWhenWorld>
  <RepairedInRest>true</RepairedInRest>
  <BehaviorOnNoDurability>NotSet</BehaviorOnNoDurability>
  <CastType>DrinkWater</CastType>
  <CastModifier>Immobilized</CastModifier>
  <CastLocomotionEnabled>false</CastLocomotionEnabled>
  <MobileCastMovementMult>-1</MobileCastMovementMult>
  <CastSheatheRequired>1</CastSheatheRequired>
  <OverrideSellModifier>-1</OverrideSellModifier>
  <Tags>
    <string>Drink</string>
    <string>Consummable</string>
    <string>Item</string>
  </Tags>
  <StatsHolder>
    <BaseValue>8</BaseValue>
    <RawWeight>0.5</RawWeight>
    <MaxDurability>-1</MaxDurability>
  </StatsHolder>
  <EffectTransforms>
    <DM_EffectTransform>
      <TransformName>Effects</TransformName>
      <Effects>
        <DM_Effect xsi:type="DM_AffectDrink">
          <Delay>0</Delay>
          <SyncType>OwnerSync</SyncType>
          <OverrideCategory>None</OverrideCategory>
          <AffectQuantity>70</AffectQuantity>
        </DM_Effect>
        <DM_Effect xsi:type="DM_AddStatusEffect">
          <Delay>0</Delay>
          <SyncType>OwnerSync</SyncType>
          <OverrideCategory>None</OverrideCategory>
          <StatusEffect>Environment Cold Resistance</StatusEffect>
          <ChanceToContract>100</ChanceToContract>
        </DM_Effect>
        <DM_Effect xsi:type="DM_AffectBurntStamina">
          <Delay>0</Delay>
          <SyncType>OwnerSync</SyncType>
          <OverrideCategory>None</OverrideCategory>
          <AffectQuantity>15</AffectQuantity>
          <IsModifier>false</IsModifier>
        </DM_Effect>
        <DM_Effect xsi:type="DM_RemoveStatusEffect">
          <Delay>0</Delay>
          <SyncType>OwnerSync</SyncType>
          <OverrideCategory>None</OverrideCategory>
          <Status_Name>jFnA16LJaEKXCBB6JSffHA</Status_Name>
          <Status_Tag />
          <CleanseType>StatusFamily</CleanseType>
        </DM_Effect>
      </Effects>
      <EffectConditions />
      <ChildEffects />
    </DM_EffectTransform>
    <DM_EffectTransform>
      <TransformName>ActivationEffects</TransformName>
      <Effects>
        <DM_Effect xsi:type="DM_PlaySoundEffect">
          <Delay>0</Delay>
          <SyncType>OwnerSync</SyncType>
          <OverrideCategory>None</OverrideCategory>
          <Sounds>
            <Sounds>SFX_USE_DrinkPotion</Sounds>
          </Sounds>
          <Follow>false</Follow>
          <MinPitch>1</MinPitch>
          <MaxPitch>1</MaxPitch>
        </DM_Effect>
      </Effects>
      <EffectConditions />
      <ChildEffects />
    </DM_EffectTransform>
  </EffectTransforms>
</DM_Item>