<?xml version="1.0" encoding="utf-8"?>
<DM_Weapon xmlns:xsd="http://www.w3.org/2001/XMLSchema" xmlns:xsi="http://www.w3.org/2001/XMLSchema-instance">
  <gameObjectName>2110210_ObsidianGreataxe</gameObjectName>
  <saveDir>/Equipment/Weapon/MeleeWeapon</saveDir>
  <ItemID>2110210</ItemID>
  <Name>Obsidian Greataxe</Name>
  <Description>Inflicts Burning on enemies.</Description>
  <LegacyItemID>2110215</LegacyItemID>
  <IsPickable>true</IsPickable>
  <IsUsable>false</IsUsable>
  <QtyRemovedOnUse>1</QtyRemovedOnUse>
  <GroupItemInDisplay>false</GroupItemInDisplay>
  <HasPhysicsWhenWorld>false</HasPhysicsWhenWorld>
  <RepairedInRest>true</RepairedInRest>
  <BehaviorOnNoDurability>NotSet</BehaviorOnNoDurability>
  <CastType>NONE</CastType>
  <CastModifier>Immobilized</CastModifier>
  <CastLocomotionEnabled>false</CastLocomotionEnabled>
  <MobileCastMovementMult>-1</MobileCastMovementMult>
  <CastSheatheRequired>1</CastSheatheRequired>
  <OverrideSellModifier>-1</OverrideSellModifier>
  <Tags>
    <string>2 Handed</string>
    <string>Weapon</string>
    <string>Item</string>
    <string>Axe</string>
    <string>DecraftIron_Large</string>
    <string>Decraft</string>
    <string>Brutal</string>
    <string>Family</string>
    <string>Obsidian</string>
    <string>Main Weapon</string>
  </Tags>
  <StatsHolder xsi:type="DM_WeaponStats">
    <BaseValue>375</BaseValue>
    <RawWeight>6</RawWeight>
    <MaxDurability>325</MaxDurability>
    <Damage_Resistance>
      <float>0</float>
      <float>0</float>
      <float>0</float>
      <float>0</float>
      <float>0</float>
      <float>0</float>
      <float>0</float>
      <float>0</float>
      <float>0</float>
    </Damage_Resistance>
    <Impact_Resistance>7.8</Impact_Resistance>
    <Damage_Protection>0</Damage_Protection>
    <Damage_Bonus>
      <float>0</float>
      <float>0</float>
      <float>0</float>
      <float>0</float>
      <float>0</float>
      <float>0</float>
      <float>0</float>
      <float>0</float>
      <float>0</float>
    </Damage_Bonus>
    <Stamina_Use_Penalty>0</Stamina_Use_Penalty>
    <Mana_Use_Modifier>0</Mana_Use_Modifier>
    <Movement_Penalty>0</Movement_Penalty>
    <Pouch_Bonus>0</Pouch_Bonus>
    <Heat_Protection>0</Heat_Protection>
    <Cold_Protection>0</Cold_Protection>
    <Corruption_Protection>0</Corruption_Protection>
    <Cooldown_Reduction>-0</Cooldown_Reduction>
    <Hunger_Affect>0</Hunger_Affect>
    <Thirst_Affect>0</Thirst_Affect>
    <Fatigue_Affect>0</Fatigue_Affect>
    <BarrierProtection>0</BarrierProtection>
    <GlobalStatusEffectResistance>0</GlobalStatusEffectResistance>
    <StaminaRegenModifier>0</StaminaRegenModifier>
    <AttackSpeed>1</AttackSpeed>
    <BaseDamage>
      <Damages>
        <Damage>18.5</Damage>
        <Damage_Type>Physical</Damage_Type>
      </Damages>
      <Damages>
        <Damage>18.5</Damage>
        <Damage_Type>Fire</Damage_Type>
      </Damages>
    </BaseDamage>
    <Impact>33</Impact>
    <StamCost>6.875</StamCost>
    <AutoGenerateAttackData>false</AutoGenerateAttackData>
    <Attacks>
      <AttackData>
        <StamCost>6.875</StamCost>
        <Knockback>33</Knockback>
        <AttackSpeed>1</AttackSpeed>
        <Damage>
          <float>18.5</float>
          <float>18.5</float>
        </Damage>
      </AttackData>
      <AttackData>
        <StamCost>6.875</StamCost>
        <Knockback>33</Knockback>
        <AttackSpeed>1</AttackSpeed>
        <Damage>
          <float>18.5</float>
          <float>18.5</float>
        </Damage>
      </AttackData>
      <AttackData>
        <StamCost>10.3125</StamCost>
        <Knockback>42.9</Knockback>
        <AttackSpeed>1.1</AttackSpeed>
        <Damage>
          <float>24.05</float>
          <float>24.05</float>
        </Damage>
      </AttackData>
      <AttackData>
        <StamCost>9.453125</StamCost>
        <Knockback>42.9</Knockback>
        <AttackSpeed>1.1</AttackSpeed>
        <Damage>
          <float>24.05</float>
          <float>24.05</float>
        </Damage>
      </AttackData>
      <AttackData>
        <StamCost>9.453125</StamCost>
        <Knockback>42.9</Knockback>
        <AttackSpeed>1.1</AttackSpeed>
        <Damage>
          <float>24.05</float>
          <float>24.05</float>
        </Damage>
      </AttackData>
    </Attacks>
  </StatsHolder>
  <EffectTransforms>
    <DM_EffectTransform>
      <TransformName>HitEffects</TransformName>
      <Effects>
        <DM_Effect xsi:type="DM_AddStatusEffectBuildUp">
          <Delay>0</Delay>
          <SyncType>OwnerSync</SyncType>
          <OverrideCategory>None</OverrideCategory>
          <StatusEffect>Burning</StatusEffect>
          <Buildup>33</Buildup>
          <BuildUpMultiplier>1</BuildUpMultiplier>
          <BypassCounter>false</BypassCounter>
        </DM_Effect>
      </Effects>
      <EffectConditions />
      <ChildEffects />
    </DM_EffectTransform>
  </EffectTransforms>
  <EquipSlot>RightHand</EquipSlot>
  <TwoHandType>TwoHandedRight</TwoHandType>
  <IKType>None</IKType>
  <VisualDetectabilityAdd>0</VisualDetectabilityAdd>
  <WeaponType>Axe_2H</WeaponType>
  <Unblockable>false</Unblockable>
  <SwingSound>Default</SwingSound>
  <SpecialIsZoom>false</SpecialIsZoom>
  <MaxProjectileShots>-1</MaxProjectileShots>
  <BaseHealthAbsorbRatio>0</BaseHealthAbsorbRatio>
  <BaseMaxHealthAbsorbRatio>0</BaseMaxHealthAbsorbRatio>
  <IgnoreHalfResistances>false</IgnoreHalfResistances>
</DM_Weapon>