<?xml version="1.0" encoding="utf-8"?>
<ContainerSummary xmlns:xsi="http://www.w3.org/2001/XMLSchema-instance" xmlns:xsd="http://www.w3.org/2001/XMLSchema">
  <Name>Legacy Chest</Name>
  <ItemID>0</ItemID>
  <Locations_Found>
    <QuantityHolder>
      <Name>Chersonese:Cierzo Storage</Name>
      <Quantity>1</Quantity>
    </QuantityHolder>
    <QuantityHolder>
      <Name>Hallowed Marsh:Spire of Light</Name>
      <Quantity>1</Quantity>
    </QuantityHolder>
    <QuantityHolder>
      <Name>Abrassar:The Slide</Name>
      <Quantity>1</Quantity>
    </QuantityHolder>
    <QuantityHolder>
      <Name>Enmerkar Forest:Vigil Pylon</Name>
      <Quantity>1</Quantity>
    </QuantityHolder>
  </Locations_Found>
  <All_DropTables />
</ContainerSummary>